kessel/__init__.py
kessel/context.py
kessel/headers.py
kessel/helpers.py
kessel/kessel.py
kessel/ldapauth.py
kessel/logger.py
kessel/recipe.py
kessel/request.py
kessel/response.py
kessel/session.py
kessel/urlmap.py
kessel/views.py
kessel/wsgibase.py
kessel-0.5.2.dist-info/licenses/LICENCE.txt
kessel-0.5.2.dist-info/METADATA
kessel-0.5.2.dist-info/WHEEL
kessel-0.5.2.dist-info/top_level.txt
kessel-0.5.2.dist-info/RECORD
